hbasedriver/Connection.py
hbasedriver/__init__.py
hbasedriver/master.py
hbasedriver/meta_server.py
hbasedriver/region.py
hbasedriver/regionserver.py
hbasedriver/request.py
hbasedriver/response.py
hbasedriver/zk.py
hbasedriver/client/__init__.py
hbasedriver/client/client.py
hbasedriver/client/table.py
hbasedriver/exceptions/RemoteException.py
hbasedriver/exceptions/__init__.py
hbasedriver/model/__init__.py
hbasedriver/model/cell.py
hbasedriver/model/row.py
hbasedriver/operations/__init__.py
hbasedriver/operations/column_family_builder.py
hbasedriver/operations/delete.py
hbasedriver/operations/get.py
hbasedriver/operations/put.py
hbasedriver/operations/scan.py
hbasedriver/protobuf_py/AccessControl_pb2.py
hbasedriver/protobuf_py/AccessControl_pb2.pyi
hbasedriver/protobuf_py/Admin_pb2.py
hbasedriver/protobuf_py/Admin_pb2.pyi
hbasedriver/protobuf_py/BucketCacheEntry_pb2.py
hbasedriver/protobuf_py/BucketCacheEntry_pb2.pyi
hbasedriver/protobuf_py/Cell_pb2.py
hbasedriver/protobuf_py/Cell_pb2.pyi
hbasedriver/protobuf_py/Client_pb2.py
hbasedriver/protobuf_py/Client_pb2.pyi
hbasedriver/protobuf_py/ClusterId_pb2.py
hbasedriver/protobuf_py/ClusterId_pb2.pyi
hbasedriver/protobuf_py/ClusterStatus_pb2.py
hbasedriver/protobuf_py/ClusterStatus_pb2.pyi
hbasedriver/protobuf_py/Comparator_pb2.py
hbasedriver/protobuf_py/Comparator_pb2.pyi
hbasedriver/protobuf_py/Encryption_pb2.py
hbasedriver/protobuf_py/Encryption_pb2.pyi
hbasedriver/protobuf_py/ErrorHandling_pb2.py
hbasedriver/protobuf_py/ErrorHandling_pb2.pyi
hbasedriver/protobuf_py/FS_pb2.py
hbasedriver/protobuf_py/FS_pb2.pyi
hbasedriver/protobuf_py/Filter_pb2.py
hbasedriver/protobuf_py/Filter_pb2.pyi
hbasedriver/protobuf_py/HBase_pb2.py
hbasedriver/protobuf_py/HBase_pb2.pyi
hbasedriver/protobuf_py/HFile_pb2.py
hbasedriver/protobuf_py/HFile_pb2.pyi
hbasedriver/protobuf_py/LoadBalancer_pb2.py
hbasedriver/protobuf_py/LoadBalancer_pb2.pyi
hbasedriver/protobuf_py/LockService_pb2.py
hbasedriver/protobuf_py/LockService_pb2.pyi
hbase_driver-0.0.14.dist-info/LICENSE
hbase_driver-0.0.14.dist-info/METADATA
hbase_driver-0.0.14.dist-info/WHEEL
hbase_driver-0.0.14.dist-info/top_level.txt
hbase_driver-0.0.14.dist-info/RECORD
