Metadata-Version: 2.1
Name: hbase-driver
Version: 0.0.14
Project-URL: Homepage, https://github.com/innovationb1ue/hbase-driver
Project-URL: Issues, https://github.com/innovationb1ue/hbase-driver/issues
License-File: LICENSE
Requires-Dist: kazoo
